Html_txt
