Metadata-Version: 2.1
Name: Html-txt
Version: 1.0.0.3
Summary: Sending urls get responce as html text
Home-page: https://www.facebook.com/bk4human
Author: Mahdi Hasan Shuvo
Author-email: shvo.mex@gmail.com
License: UNKNOWN
Platform: UNKNOWN
Classifier: Programming Language :: Python :: 3
Classifier: License :: OSI Approved :: MIT License
Classifier: Operating System :: OS Independent
